simple_operation
