Metadata-Version: 1.0
Name: simple-operation
Version: 0.1.1
Summary: simple operation util
Home-page: UNKNOWN
Author: UNKNOWN
Author-email: UNKNOWN
License: MIT
Platform: UNKNOWN
